SunSip/__init__.py
SunSip/__main__.py
SunSip/setup.py
SunSip-1.0.2.dist-info/METADATA
SunSip-1.0.2.dist-info/WHEEL
SunSip-1.0.2.dist-info/top_level.txt
SunSip-1.0.2.dist-info/RECORD
