Metadata-Version: 2.1
Name: SunSip
Version: 1.0.2
Summary: SunSip: Easy Programming Language for Dummies
Home-page: https://github.com/TvoozMagnificent/SunSip
Author: NumberBasher
Author-email: luchang1106@icloud.com
License: MIT
Platform: UNKNOWN
Classifier: License :: OSI Approved :: MIT License
Classifier: Programming Language :: Python :: 3
Requires-Dist: rich
